utils/__init__.py
utils/aws_helper.py
utils/date_helper.py
utils/drive_helper.py
utils/email_helper.py
utils/slack_helper.py
utils/spark_helper.py
utils/tableau_helper.py
example_pkg_data_pomelo_bi-0.0.1.dist-info/METADATA
example_pkg_data_pomelo_bi-0.0.1.dist-info/WHEEL
example_pkg_data_pomelo_bi-0.0.1.dist-info/top_level.txt
example_pkg_data_pomelo_bi-0.0.1.dist-info/RECORD
